hnt_sap_financeiro/__init__.py
hnt_sap_financeiro/fb02_anexo_transaction.py
hnt_sap_financeiro/fb02_transaction.py
hnt_sap_financeiro/fv60_transaction.py
hnt_sap_financeiro/hnt_sap_exception.py
hnt_sap_financeiro/hnt_sap_gui.py
hnt_sap_financeiro/sap_status_bar.py
hnt_sap_financeiro/common/sap_status_bar.py
hnt_sap_financeiro/common/session.py
hnt_sap_financeiro/common/tx_result.py
hnt_sap_financeiro_library-0.0.19.dist-info/METADATA
hnt_sap_financeiro_library-0.0.19.dist-info/WHEEL
hnt_sap_financeiro_library-0.0.19.dist-info/top_level.txt
hnt_sap_financeiro_library-0.0.19.dist-info/RECORD
