Metadata-Version: 2.1
Name: hnt_sap_financeiro_library
Version: 0.0.19
Summary: Lib to access sap gui to run transactions
Author: Pepe
License: MIT License
Keywords: nota_fiscal
Requires-Dist: python-dotenv
Requires-Dist: hnt-jira-library
Requires-Dist: robotframework-sapguilibrary
